bsparse/__init__.py
bsparse/anserini.py
bsparse/cli.py
bsparse/commands.py
bsparse/convert.py
bsparse/datasets.py
bsparse/jsonl.py
bsparse/models.py
bsparse/seismic.py
bsparse/utils.py
bsparse-0.1.0.dist-info/licenses/LICENSE
bsparse-0.1.0.dist-info/METADATA
bsparse-0.1.0.dist-info/WHEEL
bsparse-0.1.0.dist-info/top_level.txt
bsparse-0.1.0.dist-info/RECORD
