Metadata-Version: 2.4
Name: bsparse
Version: 0.1.0
Summary: toolkit for creating and searching sparse representations
Home-page: https://github.com/hltcoe/bsparse
Author: Andrew Yates
Author-email: first-then-last@mail-service-by-g.com
Classifier: Programming Language :: Python :: 3
Classifier: Operating System :: OS Independent
Requires-Python: >=3.9
License-File: LICENSE
Requires-Dist: ir_datasets
Requires-Dist: numpy
Requires-Dist: torch
Requires-Dist: tqdm
Requires-Dist: transformers
Dynamic: author
Dynamic: author-email
Dynamic: classifier
Dynamic: description
Dynamic: description-content-type
Dynamic: home-page
Dynamic: license-file
Dynamic: requires-dist
Dynamic: requires-python
Dynamic: summary
